helloworld/__init__.py
helloworld/helloworld.py
harrytsz02-0.0.1.dist-info/LICENSELICENSE.txt
harrytsz02-0.0.1.dist-info/METADATA
harrytsz02-0.0.1.dist-info/WHEEL
harrytsz02-0.0.1.dist-info/top_level.txt
harrytsz02-0.0.1.dist-info/RECORD
