Metadata-Version: 2.1
Name: harrytsz02
Version: 0.0.1
Summary: string to date
Home-page: UNKNOWN
Author: harrytsz
Author-email: taosizhan@gmail.com
License: MIT
Platform: UNKNOWN
